{"type":"page","meta":{"indexable":true,"title":"Todo，网站专用任务管理器","description":"Foudroyer 的 Todo 帮助您管理每个网站所需完成的所有任务，从内容创建到错误修复。"},"id":"617f902b-9695-48cb-8d7c-b51330335b87","published_at":"2025-07-09T19:48:27.597Z","updated_at":"2025-07-09T19:48:27.597Z","url":"todo","lang":"zh","content":[{"type":"marketing/product-of-the-day","id":"3ac14590-3228-4e15-b5ce-df967e40b292"},{"type":"marketing/hero","label":{"value":"保持组织有序，发展您的业务","component":"p"},"title":{"value":"**待办事项列表集中化**，_轻松发展每个网站_","component":"h1"},"description":"跟踪每个网站需要做的一切。无论是发布博客文章、修复布局错误，还是规划下一个功能，所有任务都在它们所属的网站上进行。"},{"type":"marketing/buttons","buttons":[{"type":"authentication","label":"创建您的第一个待办事项列表","size":"lg","variant":"secondary"}]},{"type":"marketing/users-and-stars","id":"3ac14590-3228-4e15-b5ce-df967c40b292"},{"type":"marketing/testimonials","show":true},{"type":"marketing/features","label":{"value":"为网络团队打造的任务","component":"p"},"title":{"value":"您网站的待办事项列表","component":"h2"},"description":"从内容更新到质量保证再到性能评估——将您团队的所有工作按网站集中在一个地方进行组织。","features":[{"title":{"value":"为每个网站创建一个待办事项列表","component":"h3"},"description":"Foudroyer 中的每个站点都有自己的待办事项列表。保持您的工作流程清晰和专注。","video":{"autoplay":true,"alt":"灵活的任务创建","src":"../assets/todo/features/add-website.mp4","illustration":"../assets/advanced-filter-analytics.jpeg"}},{"title":{"value":"添加任务以处理任何事情","component":"h3"},"description":"添加任务用于任何事情，写作、编码、设计、性能。","video":{"autoplay":true,"alt":"灵活的任务创建","src":"../assets/todo/features/add-task.mp4","illustration":"../assets/advanced-filter-analytics.jpeg"}},{"title":{"value":"将任务标记为完成","component":"h3"},"description":"将任务标记为已完成，以跟踪您的进度。您还可以添加评论并与您的团队分享。","video":{"autoplay":true,"alt":"灵活的任务创建","src":"../assets/todo/features/accomplish-task.mp4","illustration":"../assets/advanced-filter-analytics.jpeg"}}]},{"type":"marketing/pricing","show":true,"scope":"indexation"}]}